README.md
setup.py
Flask_Cat.egg-info/PKG-INFO
Flask_Cat.egg-info/SOURCES.txt
Flask_Cat.egg-info/dependency_links.txt
Flask_Cat.egg-info/top_level.txt
flaskcat/__init__.py
flaskcat/blueprint.py