Metadata-Version: 2.1
Name: Flask-Cat
Version: 1.0.0
Summary: Flask-Cat returns a cat for each status code above 399.
Home-page: https://github.com/ZSendokame/Flask-Cat
Author: ZSendokame
License: MIT license
Platform: UNKNOWN
